README.rst
setup.cfg
setup.py
dj_webdav_storage.egg-info/PKG-INFO
dj_webdav_storage.egg-info/SOURCES.txt
dj_webdav_storage.egg-info/dependency_links.txt
dj_webdav_storage.egg-info/not-zip-safe
dj_webdav_storage.egg-info/requires.txt
dj_webdav_storage.egg-info/top_level.txt
django_webdav_storage/__init__.py
django_webdav_storage/listing.py
django_webdav_storage/models.py
django_webdav_storage/storage.py
django_webdav_storage/tests.py