Metadata-Version: 1.1
Name: dj-webdav-storage
Version: 0.6.1
Summary: This application allows you easily save media and static files into webdav storage
Home-page: https://github.com/marazmiki/django-webdav-storage
Author: Mikhail Porokhovnichenko
Author-email: marazmiki@gmail.com
License: UNKNOWN
Platform: UNKNOWN
Classifier: Environment :: Web Environment
Classifier: Programming Language :: Python :: 2.7
Classifier: Programming Language :: Python :: 3.3
Classifier: Programming Language :: Python :: 3.4
Classifier: Framework :: Django
